django_cookiejwt/__init__.py
django_cookiejwt/apps.py
django_cookiejwt/authentication.py
django_cookiejwt/conf.py
django_cookiejwt/middlewares.py
django_cookiejwt/schema.py
django_cookiejwt/serializers.py
django_cookiejwt/services.py
django_cookiejwt/urls.py
django_cookiejwt/views.py
django_cookiejwt-0.0.2.dist-info/METADATA
django_cookiejwt-0.0.2.dist-info/WHEEL
django_cookiejwt-0.0.2.dist-info/RECORD
