Metadata-Version: 2.4
Name: django-cookiejwt
Version: 0.0.2
Summary: JWT authentication using HTTP-only cookies for Django REST Framework
Project-URL: Homepage, https://github.com/muehlemann-popp/django-cookiejwt
Project-URL: Repository, https://github.com/muehlemann-popp/django-cookiejwt
Project-URL: Documentation, https://github.com/muehlemann-popp/django-cookiejwt/wiki
Project-URL: Bug Tracker, https://github.com/muehlemann-popp/django-cookiejwt/issues
Project-URL: Changelog, https://github.com/muehlemann-popp/django-cookiejwt/blob/master/CHANGELOG.md
Author-email: Andrey Kalashnikov <andrey.kalashnikov@muehlemann-popp.ch>
License: MIT
Keywords: authentication,cookies,django,jwt,rest-framework
Classifier: Development Status :: 4 - Beta
Classifier: Environment :: Web Environment
Classifier: Framework :: Django
Classifier: Framework :: Django :: 4.0
Classifier: Framework :: Django :: 4.1
Classifier: Framework :: Django :: 4.2
Classifier: Framework :: Django :: 5.0
Classifier: Intended Audience :: Developers
Classifier: License :: OSI Approved :: MIT License
Classifier: Operating System :: OS Independent
Classifier: Programming Language :: Python
Classifier: Programming Language :: Python :: 3
Classifier: Programming Language :: Python :: 3.12
Classifier: Programming Language :: Python :: 3.13
Classifier: Topic :: Internet :: WWW/HTTP
Classifier: Topic :: Security
Classifier: Topic :: Software Development :: Libraries :: Python Modules
Requires-Python: >=3.12
Requires-Dist: django>=4.0
Requires-Dist: djangorestframework-simplejwt>=5.2.0
Requires-Dist: djangorestframework>=3.14.0
Requires-Dist: drf-spectacular>=0.28.0
